Metadata-Version: 1.1
Name: django-admin-report
Version: 0.6.1
Summary: Django application and library for create reports using all power of the ORM Django
Home-page: https://github.com/mateuspadua/django-admin-report
Author: Mateus Vanzo de Padua
Author-email: mateuspaduaweb@gmail.com
License: MIT License
Keywords: report,django,admin,group_by,annotate,agregate,ORM
Platform: OS Independent
Classifier: Framework :: Django
Classifier: Intended Audience :: Developers
Classifier: License :: OSI Approved :: MIT License
Classifier: Operating System :: OS Independent
Classifier: Topic :: Software Development
Classifier: Programming Language :: Python
Classifier: Programming Language :: Python :: 2
Classifier: Programming Language :: Python :: 3
